gem/__init__.py
gemdp-0.2.dist-info/licenses/LICENSE
gemdp-0.2.dist-info/METADATA
gemdp-0.2.dist-info/WHEEL
gemdp-0.2.dist-info/top_level.txt
gemdp-0.2.dist-info/RECORD
