Metadata-Version: 2.4
Name: gemDP
Version: 0.2
Summary: Gem is a Python library that makes Minecraft Datapack/Resourcepack creation process easier
Author: UniversalShift
License: MIT
Project-URL: Homepage, https://github.com/UniversalShift/GemDP
Project-URL: Issues, https://github.com/UniversalShift/GemDP/issues
Classifier: Programming Language :: Python :: 3
Classifier: Operating System :: OS Independent
Requires-Python: >=3.9
License-File: LICENSE
Dynamic: license-file
